netbox_entraid_tools/__init__.py
netbox_entraid_tools/common.py
netbox_entraid_tools/forms.py
netbox_entraid_tools/jobs.py
netbox_entraid_tools/models.py
netbox_entraid_tools/navigation.py
netbox_entraid_tools/signals.py
netbox_entraid_tools/tasks.py
netbox_entraid_tools/template_content.py
netbox_entraid_tools/test_logging.py
netbox_entraid_tools/urls.py
netbox_entraid_tools/views.py
netbox_entraid_tools/api/__init__.py
netbox_entraid_tools/api/serializers.py
netbox_entraid_tools/api/urls.py
netbox_entraid_tools/api/views.py
netbox_entraid_tools/entra/__init__.py
netbox_entraid_tools/entra/graph.py
netbox_entraid_tools/entra/storage.py
netbox_entraid_tools/management/__init__.py
netbox_entraid_tools/management/commands/__init__.py
netbox_entraid_tools/management/commands/diagnose_logging.py
netbox_entraid_tools/management/commands/run_entraid_deprecations.py
netbox_entraid_tools/management/commands/sync_entraid_user_status.py
netbox_entraid_tools/migrations/0001_initial.py
netbox_entraid_tools/migrations/0002_settings_report_recipients_settings_report_sender.py
netbox_entraid_tools/migrations/0003_alter_settings_options.py
netbox_entraid_tools/migrations/0004_settings_treat_disabled_as_missing.py
netbox_entraid_tools/migrations/0005_settings_debug_mode.py
netbox_entraid_tools/migrations/0006_settings_local_user_accounts.py
netbox_entraid_tools/migrations/0007_rename_job_fields.py
netbox_entraid_tools/migrations/__init__.py
netbox_entraid_tools/scripts/__init__.py
netbox_entraid_tools/scripts/resolve_contact_entraid.py
netbox_entraid_tools/templates/netbox_entraid_tools/config.html
netbox_entraid_tools/templates/netbox_entraid_tools/resolve_contact_confirm.html
netbox_entraid_tools/templates/netbox_entraid_tools/update_contact_entraid.html
netbox_entraid_tools/templates/netbox_entraid_tools/buttons/contact_actions.html
netbox_entraid_tools/templates/netbox_entraid_tools/buttons/contact_list_actions.html
netbox_entraid_tools-1.0.0.dist-info/METADATA
netbox_entraid_tools-1.0.0.dist-info/WHEEL
netbox_entraid_tools-1.0.0.dist-info/entry_points.txt
netbox_entraid_tools-1.0.0.dist-info/top_level.txt
netbox_entraid_tools-1.0.0.dist-info/RECORD
