Metadata-Version: 2.4
Name: netbox-entraid-tools
Version: 1.0.0
Summary: Jobs and utilities for EntraID hygiene in NetBox
Home-page: https://github.com/bacardi-code/techops-networking-netbox-entraid-tools
Author: Bacardi -  N.I.T.
Author-email: "Bacardi -  N.I.T." <netbox@bacardi.com>
License: Apache Software License
Project-URL: Homepage, https://github.com/bacardi-code/techops-networking-netbox-entraid-tools
Project-URL: Bug Tracker, https://github.com/bacardi-code/techops-networking-netbox-entraid-tools/issues
Project-URL: Source Code, https://github.com/bacardi-code/techops-networking-netbox-entraid-tools
Classifier: Programming Language :: Python :: 3
Classifier: License :: OSI Approved :: Apache Software License
Classifier: Framework :: Django
Requires-Python: >=3.10
Requires-Dist: requests>=2.31.0
Requires-Dist: azure-identity>=1.15.0
Requires-Dist: azure-data-tables>=12.5.0
Dynamic: author
Dynamic: home-page
Dynamic: requires-python
